AUTHORS.rst
CONTRIBUTING.rst
HISTORY.rst
LICENSE
MANIFEST.in
README.rst
setup.cfg
setup.py
docs/Makefile
docs/authors.rst
docs/conf.py
docs/contributing.rst
docs/history.rst
docs/index.rst
docs/installation.rst
docs/make.bat
docs/readme.rst
docs/usage.rst
pyretroicor/__init__.py
pyretroicor/cli.py
pyretroicor/prepro.py
pyretroicor/retroicor.py
pyretroicor/util.py
pyretroicor.egg-info/PKG-INFO
pyretroicor.egg-info/SOURCES.txt
pyretroicor.egg-info/dependency_links.txt
pyretroicor.egg-info/entry_points.txt
pyretroicor.egg-info/not-zip-safe
pyretroicor.egg-info/requires.txt
pyretroicor.egg-info/top_level.txt
tests/__init__.py
tests/test_pyretroicor.py