Metadata-Version: 1.2
Name: pyretroicor
Version: 0.0.3
Summary: Python implementation of RETROICOR.
Home-page: https://github.com/htwangtw/pyretroicor
Author: Hao-Ting Wang
Author-email: htwangtw@gmail.com
License: BSD-3-clause
Keywords: fmri,physiology
Platform: UNKNOWN
Classifier: Development Status :: 2 - Pre-Alpha
Classifier: Intended Audience :: Developers
Classifier: License :: OSI Approved :: BSD License
Classifier: Natural Language :: English
Classifier: Programming Language :: Python :: 3
Classifier: Programming Language :: Python :: 3.5
Classifier: Programming Language :: Python :: 3.6
Classifier: Programming Language :: Python :: 3.7
Classifier: Programming Language :: Python :: 3.8
Requires-Python: >=3.5
